confidant_client/__init__.py
confidant_client/cli.py
confidant_client/formatter.py
confidant_client/lib/__init__.py
confidant_client/lib/cryptolib.py
confidant_client/lib/helper.py
confidant_client/services/__init__.py
confidant_client-2.7.1.dist-info/LICENSE
confidant_client-2.7.1.dist-info/METADATA
confidant_client-2.7.1.dist-info/WHEEL
confidant_client-2.7.1.dist-info/entry_points.txt
confidant_client-2.7.1.dist-info/top_level.txt
confidant_client-2.7.1.dist-info/RECORD
